<?xml version = '1.0' encoding = 'UTF-8'?>
<Relation class="oracle.dbtools.crest.model.design.logical.InheritanceRelation" name="Hierarchy_6" directorySegmentName="seg_0" id="EB9C56DA-1AC3-B156-71C3-48025885940C">
<createdBy>Scosa</createdBy>
<createdTime>2025-03-27 04:44:45 UTC</createdTime>
<ownerDesignName>MER</ownerDesignName>
<engineerTo>
<item key="AB6623C8-289C-3B2A-E712-0EFE0FFA56D6" value="true"/>
</engineerTo>
<identifying>false</identifying>
<nameOnSource>Super Type</nameOnSource>
<nameOnTarget>Sub Type</nameOnTarget>
<optionalSource>true</optionalSource>
<optionalTarget>true</optionalTarget>
<sourceEntity>313A439A-40ED-89A1-A688-E4F9CFCB0EFB</sourceEntity>
<targetEntity>E6DB25ED-5648-88C7-DE5C-DEB510DD40AA</targetEntity>
<transferable>true</transferable>
<deleteRule>NO ACTION</deleteRule>
</Relation>
